matrix_mem.v
/*
 * Matrix Memory Module
 * 2-bit wide memory with dual input ports and arbiter
 */

module matrix_mem #(parameter WIDTH = 6)(
    input clk,
    input rstn,

    input [2:0] in1_x,
    input [2:0] in1_y,
    input in1_wr_en,
    input [1:0] in1_data_in,
    input in1_data_in_valid,

    input [2:0] in2_x,
    input [2:0] in2_y,
    input in2_wr_en,
    input [1:0] in2_data_in,
    input in2_data_in_valid,

    input in_sel,

    input [1:0] init_select,

    output reg [1:0] data_out,
    output reg empty,
    output reg data_out_valid
);

reg [1:0] matrix [WIDTH*WIDTH-1:0];
wire [5:0] index;
wire [2:0] x, y;
wire wr_en;
wire [1:0] data_in;
wire data_in_valid;

assign x = in_sel ? in2_x : in1_x;
assign y = in_sel ? in2_y : in1_y;
assign wr_en = in_sel ? in2_wr_en : in1_wr_en;
assign data_in = in_sel ? in2_data_in : in1_data_in;
assign data_in_valid = in_sel ? in2_data_in_valid : in1_data_in_valid;

assign index = x*WIDTH + y;

// Check if all submarine bits (bit 0) are cleared
integer k;
always @(*) begin
    empty = 1'b1;
    for (k = 0; k < WIDTH*WIDTH; k = k + 1) begin
        if (matrix[k][0]) empty = 1'b0;
    end
end

// Auxiliary variables for wave viewer debugging - display matrix as 2D array
reg [1:0] matrix_display [0:WIDTH-1][0:WIDTH-1];
integer row, col;
always @(*) begin
    for (row = 0; row < WIDTH; row = row + 1) begin
        for (col = 0; col < WIDTH; col = col + 1) begin
            matrix_display[row][col] = matrix[row*WIDTH + col];
        end
    end
end

// Individual row signals for easier wave viewing
wire [1:0] row0 [0:WIDTH-1];
wire [1:0] row1 [0:WIDTH-1];
wire [1:0] row2 [0:WIDTH-1];
wire [1:0] row3 [0:WIDTH-1];
wire [1:0] row4 [0:WIDTH-1];
wire [1:0] row5 [0:WIDTH-1];

// Flattened row signals for wave viewer
wire [11:0] row0_flat, row1_flat, row2_flat, row3_flat, row4_flat, row5_flat;

genvar i;
generate
    for (i = 0; i < WIDTH; i = i + 1) begin : row_signals
        assign row0[i] = matrix_display[0][i];
        assign row1[i] = matrix_display[1][i];
        assign row2[i] = matrix_display[2][i];
        assign row3[i] = matrix_display[3][i];
        assign row4[i] = matrix_display[4][i];
        assign row5[i] = matrix_display[5][i];
    end
endgenerate

assign row0_flat = {row0[5], row0[4], row0[3], row0[2], row0[1], row0[0]};
assign row1_flat = {row1[5], row1[4], row1[3], row1[2], row1[1], row1[0]};
assign row2_flat = {row2[5], row2[4], row2[3], row2[2], row2[1], row2[0]};
assign row3_flat = {row3[5], row3[4], row3[3], row3[2], row3[1], row3[0]};
assign row4_flat = {row4[5], row4[4], row4[3], row4[2], row4[1], row4[0]};
assign row5_flat = {row5[5], row5[4], row5[3], row5[2], row5[1], row5[0]};

// Individual scalar signals for each matrix position (better wave viewer compatibility)
wire [1:0] m00, m01, m02, m03, m04, m05;
wire [1:0] m10, m11, m12, m13, m14, m15;
wire [1:0] m20, m21, m22, m23, m24, m25;
wire [1:0] m30, m31, m32, m33, m34, m35;
wire [1:0] m40, m41, m42, m43, m44, m45;
wire [1:0] m50, m51, m52, m53, m54, m55;

assign m00 = matrix_display[0][0]; assign m01 = matrix_display[0][1]; assign m02 = matrix_display[0][2];
assign m03 = matrix_display[0][3]; assign m04 = matrix_display[0][4]; assign m05 = matrix_display[0][5];
assign m10 = matrix_display[1][0]; assign m11 = matrix_display[1][1]; assign m12 = matrix_display[1][2];
assign m13 = matrix_display[1][3]; assign m14 = matrix_display[1][4]; assign m15 = matrix_display[1][5];
assign m20 = matrix_display[2][0]; assign m21 = matrix_display[2][1]; assign m22 = matrix_display[2][2];
assign m23 = matrix_display[2][3]; assign m24 = matrix_display[2][4]; assign m25 = matrix_display[2][5];
assign m30 = matrix_display[3][0]; assign m31 = matrix_display[3][1]; assign m32 = matrix_display[3][2];
assign m33 = matrix_display[3][3]; assign m34 = matrix_display[3][4]; assign m35 = matrix_display[3][5];
assign m40 = matrix_display[4][0]; assign m41 = matrix_display[4][1]; assign m42 = matrix_display[4][2];
assign m43 = matrix_display[4][3]; assign m44 = matrix_display[4][4]; assign m45 = matrix_display[4][5];
assign m50 = matrix_display[5][0]; assign m51 = matrix_display[5][1]; assign m52 = matrix_display[5][2];
assign m53 = matrix_display[5][3]; assign m54 = matrix_display[5][4]; assign m55 = matrix_display[5][5];

always @(posedge clk or negedge rstn) begin
    if (~rstn) begin
        data_out <= 2'b00;
        data_out_valid <= 1'b0;
        case (init_select)
            2'b00: begin
                    for (integer i = 0; i < WIDTH*WIDTH; i = i + 1) begin
                        matrix[i] <= {1'b0, (36'b000011_000001_000001_110010_000000_101100 >> i) & 1'b1};
                    end
                   end
            2'b01: begin
                    for (integer i = 0; i < WIDTH*WIDTH; i = i + 1) begin
                        matrix[i] <= {1'b0, (36'b001010_000001_000000_010111_000000_101100 >> i) & 1'b1};
                    end
                   end
            2'b10: begin
                    for (integer i = 0; i < WIDTH*WIDTH; i = i + 1) begin
                        matrix[i] <= {1'b0, (36'b010000_101000_000101_000000_101010_000010 >> i) & 1'b1};
                    end
                   end
            2'b11: begin
                    for (integer i = 0; i < WIDTH*WIDTH; i = i + 1) begin
                        matrix[i] <= {1'b0, (36'b000010_100000_001001_010100_100001_000100 >> i) & 1'b1};
                    end
                   end
        endcase

    end else begin
        data_out_valid <= 1'b0;  // Default to invalid
        
        if (data_in_valid && index < (WIDTH*WIDTH)) begin 
            if (wr_en) begin
                matrix[index] <= data_in;
            end
            data_out <= matrix[index];
            data_out_valid <= 1'b1;  // Signal valid output
        end
    end
end

endmodule

tb_matrix_mem.v
`timescale 1ns / 1ps

module tb_matrix_mem;
    parameter WIDTH = 6;
    
    reg clk, rstn;
    reg [2:0] in1_x, in1_y, in2_x, in2_y;
    reg [1:0] in1_data_in, in2_data_in, init_select;
    reg in1_wr_en, in2_wr_en, in1_data_in_valid, in2_data_in_valid, in_sel;
    wire [1:0] data_out;
    wire empty, data_out_valid;
    
    matrix_mem #(.WIDTH(WIDTH)) uut (
        .clk(clk), .rstn(rstn),
        .in1_x(in1_x), .in1_y(in1_y), .in1_wr_en(in1_wr_en),
        .in1_data_in(in1_data_in), .in1_data_in_valid(in1_data_in_valid),
        .in2_x(in2_x), .in2_y(in2_y), .in2_wr_en(in2_wr_en),
        .in2_data_in(in2_data_in), .in2_data_in_valid(in2_data_in_valid),
        .in_sel(in_sel), .init_select(init_select),
        .data_out(data_out), .empty(empty), .data_out_valid(data_out_valid)
    );
    
    always #5 clk = ~clk;
    
    initial begin
        $dumpfile("tb_matrix_mem.vcd");
        $dumpvars(0, tb_matrix_mem);
        
        clk = 0; rstn = 0; in1_wr_en = 0; in2_wr_en = 0; in_sel = 0;
        in1_data_in_valid = 0; in2_data_in_valid = 0; init_select = 0;
        #10 rstn = 1;
        
        // Test port 1 write
        in1_x = 1; in1_y = 1; in1_data_in = 2'b01; 
        in1_wr_en = 1; in1_data_in_valid = 1;
        #10 in1_wr_en = 0;
        
        // Test port 1 read (keep data_in_valid high for read)
        #10;
        if (data_out_valid && data_out == 2'b01) $display("Port 1 test PASSED");
        else $display("Port 1 read: expected 01, got %b (valid=%b)", data_out, data_out_valid);
        in1_data_in_valid = 0;
        
        // Test port 2 with arbiter
        in_sel = 1;
        in2_x = 2; in2_y = 2; in2_data_in = 2'b10;
        in2_wr_en = 1; in2_data_in_valid = 1;
        #10 in2_wr_en = 0;
        
        // Test port 2 read
        #10;
        if (data_out_valid && data_out == 2'b10) $display("Port 2 test PASSED");
        else $display("Port 2 read: expected 10, got %b (valid=%b)", data_out, data_out_valid);
        
        $display("Matrix memory verification COMPLETED");
        $finish;
    end
endmodule

tb_matrix_mem.vcd
$date
	Sun Nov  2 18:43:27 2025
$end
$version
	Icarus Verilog
$end
$timescale
	1ps
$end
$scope module tb_matrix_mem $end
$var wire 1 ! empty $end
$var wire 1 " data_out_valid $end
$var wire 2 # data_out [1:0] $end
$var parameter 32 $ WIDTH $end
$var reg 1 % clk $end
$var reg 2 & in1_data_in [1:0] $end
$var reg 1 ' in1_data_in_valid $end
$var reg 1 ( in1_wr_en $end
$var reg 3 ) in1_x [2:0] $end
$var reg 3 * in1_y [2:0] $end
$var reg 2 + in2_data_in [1:0] $end
$var reg 1 , in2_data_in_valid $end
$var reg 1 - in2_wr_en $end
$var reg 3 . in2_x [2:0] $end
$var reg 3 / in2_y [2:0] $end
$var reg 1 0 in_sel $end
$var reg 2 1 init_select [1:0] $end
$var reg 1 2 rstn $end
$scope module uut $end
$var wire 1 % clk $end
$var wire 2 3 in1_data_in [1:0] $end
$var wire 1 ' in1_data_in_valid $end
$var wire 1 ( in1_wr_en $end
$var wire 3 4 in1_x [2:0] $end
$var wire 3 5 in1_y [2:0] $end
$var wire 2 6 in2_data_in [1:0] $end
$var wire 1 , in2_data_in_valid $end
$var wire 1 - in2_wr_en $end
$var wire 3 7 in2_x [2:0] $end
$var wire 3 8 in2_y [2:0] $end
$var wire 1 0 in_sel $end
$var wire 2 9 init_select [1:0] $end
$var wire 2 : m00 [1:0] $end
$var wire 2 ; m01 [1:0] $end
$var wire 2 < m02 [1:0] $end
$var wire 2 = m03 [1:0] $end
$var wire 2 > m04 [1:0] $end
$var wire 2 ? m05 [1:0] $end
$var wire 2 @ m10 [1:0] $end
$var wire 2 A m11 [1:0] $end
$var wire 2 B m12 [1:0] $end
$var wire 2 C m13 [1:0] $end
$var wire 2 D m14 [1:0] $end
$var wire 2 E m15 [1:0] $end
$var wire 2 F m20 [1:0] $end
$var wire 2 G m21 [1:0] $end
$var wire 2 H m22 [1:0] $end
$var wire 2 I m23 [1:0] $end
$var wire 2 J m24 [1:0] $end
$var wire 2 K m25 [1:0] $end
$var wire 2 L m30 [1:0] $end
$var wire 2 M m31 [1:0] $end
$var wire 2 N m32 [1:0] $end
$var wire 2 O m33 [1:0] $end
$var wire 2 P m34 [1:0] $end
$var wire 2 Q m35 [1:0] $end
$var wire 2 R m40 [1:0] $end
$var wire 2 S m41 [1:0] $end
$var wire 2 T m42 [1:0] $end
$var wire 2 U m43 [1:0] $end
$var wire 2 V m44 [1:0] $end
$var wire 2 W m45 [1:0] $end
$var wire 2 X m50 [1:0] $end
$var wire 2 Y m51 [1:0] $end
$var wire 2 Z m52 [1:0] $end
$var wire 2 [ m53 [1:0] $end
$var wire 2 \ m54 [1:0] $end
$var wire 2 ] m55 [1:0] $end
$var wire 1 2 rstn $end
$var wire 3 ^ y [2:0] $end
$var wire 3 _ x [2:0] $end
$var wire 1 ` wr_en $end
$var wire 12 a row5_flat [11:0] $end
$var wire 12 b row4_flat [11:0] $end
$var wire 12 c row3_flat [11:0] $end
$var wire 12 d row2_flat [11:0] $end
$var wire 12 e row1_flat [11:0] $end
$var wire 12 f row0_flat [11:0] $end
$var wire 6 g index [5:0] $end
$var wire 1 h data_in_valid $end
$var wire 2 i data_in [1:0] $end
$var parameter 32 j WIDTH $end
$var reg 2 k data_out [1:0] $end
$var reg 1 " data_out_valid $end
$var reg 1 ! empty $end
$var integer 32 l col [31:0] $end
$var integer 32 m k [31:0] $end
$var integer 32 n row [31:0] $end
$scope begin row_signals[0] $end
$var parameter 2 o i $end
$upscope $end
$scope begin row_signals[1] $end
$var parameter 2 p i $end
$upscope $end
$scope begin row_signals[2] $end
$var parameter 3 q i $end
$upscope $end
$scope begin row_signals[3] $end
$var parameter 3 r i $end
$upscope $end
$scope begin row_signals[4] $end
$var parameter 4 s i $end
$upscope $end
$scope begin row_signals[5] $end
$var parameter 4 t i $end
$upscope $end
$scope begin $ivl_for_loop0 $end
$var integer 32 u i [31:0] $end
$upscope $end
$scope begin $ivl_for_loop1 $end
$var integer 32 v i [31:0] $end
$upscope $end
$scope begin $ivl_for_loop2 $end
$var integer 32 w i [31:0] $end
$upscope $end
$scope begin $ivl_for_loop3 $end
$var integer 32 x i [31:0] $end
$upscope $end
$upscope $end
$upscope $end
$enddefinitions $end
$comment Show the parameter values. $end
$dumpall
b101 t
b100 s
b11 r
b10 q
b1 p
b0 o
b110 j
b110 $
$end
#0
$dumpvars
bx x
bx w
bx v
b100100 u
b110 n
b100100 m
b110 l
b0 k
bx i
0h
bx g
b10001010000 f
b0 e
b10100000100 d
b1 c
b1 b
b101 a
0`
bx _
bx ^
b0 ]
b0 \
b0 [
b0 Z
b1 Y
b1 X
b0 W
b0 V
b0 U
b0 T
b0 S
b1 R
b0 Q
b0 P
b0 O
b0 N
b0 M
b1 L
b1 K
b1 J
b0 I
b0 H
b1 G
b0 F
b0 E
b0 D
b0 C
b0 B
b0 A
b0 @
b1 ?
b0 >
b1 =
b1 <
b0 ;
b0 :
b0 9
bx 8
bx 7
bx 6
bx 5
bx 4
bx 3
02
b0 1
00
bx /
bx .
0-
0,
bx +
bx *
bx )
0(
0'
bx &
0%
b0 #
0"
0!
$end
#5000
b100100 u
1%
#10000
b111 g
1h
1`
b1 i
b1 ^
b1 _
0%
1'
1(
b1 &
b1 3
b1 *
b1 5
b1 )
b1 4
12
#15000
b100100 m
0!
b1 A
b100 e
b110 l
b110 n
1"
1%
#20000
0`
0%
0(
#25000
b1 #
b1 k
1"
1%
#30000
b1110 g
b10 _
b10 ^
1`
b10 i
0%
1,
1-
b10 +
b10 6
b10 /
b10 8
b10 .
b10 7
10
0'
#35000
b10 H
b10100100100 d
b110 l
b110 n
b100100 m
0!
b0 #
b0 k
1"
1%
#40000
0`
0%
0-
#45000
b10 #
b10 k
1"
1%
