bfs.v
/*
 * BFS (Breadth-First Search) Module
 * Used for submarine sink detection with external memory interface
 * Split into Main FSM and Neighbor-Check FSM
 */

module bfs #(parameter WIDTH = 6) (
    input clk,
    input rstn,

    input [2:0] x,
    input [2:0] y,

    // External memory interface
    output reg [2:0] mem_addr_x,
    output reg [2:0] mem_addr_y,
    output reg mem_wr_en,
    output reg [1:0] mem_wr_data,
    output reg mem_in_valid,
    input [1:0] mem_rd_data,
    input mem_ready,

    input bfs_start,

    output reg bfs_sink,
    output reg bfs_done
);

reg [2:0] orig_x;
reg [2:0] orig_y;

wire [2:0] x_right;
wire [2:0] x_left;
wire [2:0] y_upper;
wire [2:0] y_lower;
assign x_right = (orig_x == WIDTH-1) ?  WIDTH-1 : orig_x + 1;
assign x_left = (orig_x == 0) ?         0 : orig_x - 1;
assign y_upper = (orig_y == WIDTH-1) ?  WIDTH-1 : orig_y + 1;
assign y_lower = (orig_y == 0) ?        0 : orig_y - 1; 

// Main FSM states
reg [3:0] bfs_state;
reg [3:0] bfs_next_state;
localparam BFS_LOAD = 4'b0000;
localparam BFS_CHECK = 4'b0010;
localparam BFS_CLEAR = 4'b1000;
localparam BFS_DONE = 4'b1110;
localparam DELAY = 4'b1111;

// Neighbor Check FSM states
reg [2:0] check_state;
reg [2:0] check_next_state;
localparam CHECK_IDLE = 3'b000;
localparam X_L = 3'b001;
localparam X_R = 3'b010;
localparam Y_U = 3'b011;
localparam Y_D = 3'b100;
localparam CHECK_FOUND = 3'b101;
localparam CHECK_DELAY = 3'b110;

// State name debugging
reg [8*8-1:0] bfs_state_name;
always @(bfs_state) begin
    case (bfs_state) 
        BFS_LOAD : bfs_state_name <= "LOAD";
        BFS_CHECK : bfs_state_name <= "CHECK";
        BFS_CLEAR : bfs_state_name <= "CLEAR";
        BFS_DONE : bfs_state_name <= "DONE";
        DELAY : bfs_state_name <= "DELAY";
        default: bfs_state_name <= "UNKNOWN";
    endcase
end

reg [8*8-1:0] check_state_name;
always @(check_state) begin
    case (check_state) 
        CHECK_IDLE : check_state_name <= "IDLE";
        X_L : check_state_name <= "X_L";
        X_R : check_state_name <= "X_R";
        Y_U : check_state_name <= "Y_U";
        Y_D : check_state_name <= "Y_D";
        CHECK_FOUND : check_state_name <= "C_FOUND";
        CHECK_DELAY : check_state_name <= "C_DELAY";
        default: check_state_name <= "UNKNOWN";
    endcase
end

// Inter-FSM communication
reg check_start;
reg check_done_sig;

// Neighbor detection variables
reg found_gray;
reg found_white;
wire found;
assign found = found_gray | found_white;

reg [2:0] gray_x;
reg [2:0] gray_y;
reg [2:0] cell_count;  // Changed from 2 bits to 3 bits to handle up to 4 neighbors

// Main BFS FSM
always @(posedge clk or negedge rstn) begin 
    if (~rstn) begin 
        bfs_sink <= 1'b0;
        bfs_done <= 1'b0;
        bfs_state <= BFS_LOAD;
        bfs_next_state <= BFS_LOAD;
        check_start <= 1'b0;
        orig_x <= 3'b000;
        orig_y <= 3'b000;
        found_gray <= 1'b0;
        found_white <= 1'b0;
        cell_count <= 3'b000;
        gray_x <= 3'b000;
        gray_y <= 3'b000;
        mem_addr_x <= 3'b0;
        mem_addr_y <= 3'b0;
        mem_wr_en <= 1'b0;
        mem_wr_data <= 2'b00;
        mem_in_valid <= 1'b0;
    end else begin
        case (bfs_state)
            BFS_LOAD : begin
                if (bfs_start) begin
                    orig_x <= x;
                    orig_y <= y;
                    bfs_state <= BFS_CHECK;
                    found_gray <= 1'b0;
                    found_white <= 1'b0;
                    cell_count <= 0;
                end
            end
            
            BFS_CHECK : begin
                check_start <= 1'b1;  // Start neighbor check FSM
                if (check_done_sig) begin
                    check_start <= 1'b0;
                    
                    // Handle memory writing based on neighbor check results
                    if (cell_count > 1) begin
                        mem_addr_x <= orig_x;
                        mem_addr_y <= orig_y;
                        mem_wr_en <= 1'b1;
                        mem_wr_data <= 2'b10;  // Gray
                        mem_in_valid <= 1'b1;
                        bfs_sink <= 1'b0;
                        bfs_state <= DELAY;
                        bfs_next_state <= BFS_DONE;
                    end else if (cell_count == 0) begin 
                        mem_addr_x <= orig_x;
                        mem_addr_y <= orig_y;
                        mem_wr_en <= 1'b1;
                        mem_wr_data <= 2'b00;  // Clear the original bit
                        mem_in_valid <= 1'b1;
                        bfs_sink <= 1'b1;  // Sink - no neighbors found
                        bfs_state <= DELAY;
                        bfs_next_state <= BFS_DONE;
                    /* at this point, we found 1 cell */
                    end else if (found_white) begin
                        mem_addr_x <= orig_x;
                        mem_addr_y <= orig_y;
                        mem_wr_en <= 1'b1;
                        mem_wr_data <= 2'b10;  // Gray
                        mem_in_valid <= 1'b1;
                        bfs_sink <= 1'b0;
                        bfs_state <= DELAY;
                        bfs_next_state <= BFS_DONE;
                    end else if (found_gray) begin
                        bfs_sink <= 1'b0;
                        mem_addr_x <= orig_x;
                        mem_addr_y <= orig_y;
                        mem_wr_en <= 1'b1;
                        mem_wr_data <= 2'b00;  // Clear the original bit
                        mem_in_valid <= 1'b1;
                        bfs_state <= DELAY;
                        bfs_state <= BFS_CLEAR;
                    end
                end
            end
            
            BFS_CLEAR : begin
                orig_x <= gray_x;
                orig_y <= gray_y;
                found_gray <= 1'b0;
                found_white <= 1'b0;
                cell_count <= 3'b000;
                bfs_state <= BFS_CHECK;
            end
            
            BFS_DONE : begin
                bfs_done <= 1'b1;
                mem_wr_en <= 1'b0;
                if (~bfs_start) begin   
                    bfs_state <= BFS_LOAD;
                    bfs_done <= 1'b0;
                    bfs_sink <= 1'b0;
                end
            end
            
            DELAY: begin
                mem_in_valid <= 1'b0;  // Clear valid signal
                mem_wr_en <= 1'b0;
                if (mem_ready) begin
                    bfs_state <= bfs_next_state;
                end
            end
        endcase
    end
end

// Neighbor Check FSM
always @(posedge clk or negedge rstn) begin 
    if (~rstn) begin 
        check_state <= CHECK_IDLE;
        check_next_state <= CHECK_IDLE;
        check_done_sig <= 1'b0;
    end else begin
        case (check_state)
            CHECK_IDLE : begin
                if (check_start) begin
                    found_gray <= 1'b0;
                    found_white <= 1'b0;
                    cell_count <= 3'b000;
                    check_done_sig <= 1'b0;
                    mem_addr_x <= x_left;
                    mem_addr_y <= orig_y;
                    mem_wr_en <= 1'b0;
                    mem_in_valid <= 1'b1;
                    check_state <= CHECK_DELAY;
                    check_next_state <= X_L;
                end
            end
            
            X_L : begin
                // Only count if this is a valid neighbor (not same as current position)
                if (x_left != orig_x) begin
                    found_gray <= found_gray | mem_rd_data[1];
                    found_white <= found_white | mem_rd_data[0];
                    
                    if (mem_rd_data[1] | mem_rd_data[0]) begin
                        cell_count <= cell_count + 1;
                    end

                    if (mem_rd_data[1]) begin
                        gray_x <= mem_addr_x;
                        gray_y <= mem_addr_y;
                    end 
                end

                mem_addr_x <= x_right;
                mem_addr_y <= orig_y;
                mem_wr_en <= 1'b0;
                mem_in_valid <= 1'b1;
                check_state <= CHECK_DELAY;
                check_next_state <= X_R;
            end
            
            X_R : begin
                // Only count if this is a valid neighbor (not same as current position)
                if (x_right != orig_x) begin
                    found_gray <= found_gray | mem_rd_data[1];
                    found_white <= found_white | mem_rd_data[0];
                    
                    if (mem_rd_data[1] | mem_rd_data[0]) begin
                        cell_count <= cell_count + 1;
                    end

                    if (mem_rd_data[1]) begin
                        gray_x <= mem_addr_x;
                        gray_y <= mem_addr_y;
                    end 
                end 
                
                mem_addr_x <= orig_x;
                mem_addr_y <= y_upper;
                mem_wr_en <= 1'b0;
                mem_in_valid <= 1'b1;
                check_state <= CHECK_DELAY;
                check_next_state <= Y_U;
            end
            
            Y_U : begin
                // Only count if this is a valid neighbor (not same as current position)
                if (y_upper != orig_y) begin
                    found_gray <= found_gray | mem_rd_data[1];
                    found_white <= found_white | mem_rd_data[0];
                    
                    if (mem_rd_data[1] | mem_rd_data[0]) begin
                        cell_count <= cell_count + 1;
                    end

                    if (mem_rd_data[1]) begin
                        gray_x <= mem_addr_x;
                        gray_y <= mem_addr_y;
                    end 
                end
                
                mem_addr_x <= orig_x;
                mem_addr_y <= y_lower;
                mem_wr_en <= 1'b0;
                mem_in_valid <= 1'b1;
                check_state <= CHECK_DELAY;
                check_next_state <= Y_D;
            end
            
            Y_D : begin
                // Only count if this is a valid neighbor (not same as current position)
                if (y_lower != orig_y) begin
                    found_gray <= found_gray | mem_rd_data[1];
                    found_white <= found_white | mem_rd_data[0];
                    
                    if (mem_rd_data[1] | mem_rd_data[0]) begin
                        cell_count <= cell_count + 1;
                    end

                    if (mem_rd_data[1]) begin
                        gray_x <= mem_addr_x;
                        gray_y <= mem_addr_y;
                    end 
                end 
                
                check_state <= CHECK_FOUND;
            end
            
            CHECK_FOUND : begin
                // Only signal completion - no memory writing
                check_done_sig <= 1'b1;
                if (check_start == 1'b0) begin
                    check_state <= CHECK_IDLE;
                    check_done_sig <= 1'b0;
                end
            end
            
            CHECK_DELAY: begin
                mem_in_valid <= 1'b0;  // Clear valid signal
                mem_wr_en <= 1'b0;
                if (mem_ready) begin
                    check_state <= check_next_state;
                end
            end
        endcase
    end
end

endmodule

tb_bfs.v
`timescale 1ns / 1ps

module tb_bfs;
    parameter WIDTH = 6;
    
    reg clk, rstn, bfs_start;
    reg [2:0] x, y;
    reg [1:0] mem_rd_data;
    reg mem_ready;
    wire [2:0] mem_addr_x, mem_addr_y;
    wire [1:0] mem_wr_data;
    wire mem_wr_en, mem_in_valid, bfs_sink, bfs_done;
    
    bfs #(.WIDTH(WIDTH)) uut (
        .clk(clk), .rstn(rstn), .bfs_start(bfs_start),
        .x(x), .y(y),
        .mem_addr_x(mem_addr_x), .mem_addr_y(mem_addr_y),
        .mem_wr_data(mem_wr_data), .mem_rd_data(mem_rd_data),
        .mem_wr_en(mem_wr_en), .mem_in_valid(mem_in_valid),
        .mem_ready(mem_ready),
        .bfs_sink(bfs_sink), .bfs_done(bfs_done)
    );
    
    always #5 clk = ~clk;
    
    // Simple memory model
    reg [1:0] test_mem [0:35];
    
    // Flattened memory signals for wave viewer
    wire [71:0] mem_flat;
    wire [11:0] row0_mem, row1_mem, row2_mem, row3_mem, row4_mem, row5_mem;
    
    assign mem_flat = {test_mem[35], test_mem[34], test_mem[33], test_mem[32], test_mem[31], test_mem[30],
                       test_mem[29], test_mem[28], test_mem[27], test_mem[26], test_mem[25], test_mem[24],
                       test_mem[23], test_mem[22], test_mem[21], test_mem[20], test_mem[19], test_mem[18],
                       test_mem[17], test_mem[16], test_mem[15], test_mem[14], test_mem[13], test_mem[12],
                       test_mem[11], test_mem[10], test_mem[9], test_mem[8], test_mem[7], test_mem[6],
                       test_mem[5], test_mem[4], test_mem[3], test_mem[2], test_mem[1], test_mem[0]};
    
    assign row0_mem = {test_mem[5], test_mem[4], test_mem[3], test_mem[2], test_mem[1], test_mem[0]};
    assign row1_mem = {test_mem[11], test_mem[10], test_mem[9], test_mem[8], test_mem[7], test_mem[6]};
    assign row2_mem = {test_mem[17], test_mem[16], test_mem[15], test_mem[14], test_mem[13], test_mem[12]};
    assign row3_mem = {test_mem[23], test_mem[22], test_mem[21], test_mem[20], test_mem[19], test_mem[18]};
    assign row4_mem = {test_mem[29], test_mem[28], test_mem[27], test_mem[26], test_mem[25], test_mem[24]};
    assign row5_mem = {test_mem[35], test_mem[34], test_mem[33], test_mem[32], test_mem[31], test_mem[30]};
    
    always @(posedge clk) begin
        if (mem_in_valid) begin
            if (mem_wr_en)
                test_mem[mem_addr_y*WIDTH + mem_addr_x] <= mem_wr_data;
            mem_rd_data <= test_mem[mem_addr_y*WIDTH + mem_addr_x];
            mem_ready <= 1;
        end else begin
            mem_ready <= 0;
        end
    end
    
    initial begin
        $dumpfile("tb_bfs.vcd");
        $dumpvars(0, tb_bfs);
        
        clk = 0; rstn = 0; bfs_start = 0; mem_ready = 0;
        
        // Initialize test pattern
        for (integer i = 0; i < 36; i = i + 1) test_mem[i] = 2'b00;
        test_mem[7] = 2'b01;  // (1,1)
        test_mem[8] = 2'b01;  // (2,1)
        test_mem[13] = 2'b01; // (1,2)
        
        #10 rstn = 1;
        #10 x = 1; y = 1; bfs_start = 1;
        
        wait(bfs_done);
        #10 bfs_start = 0;
        #10 x = 2; y = 1; bfs_start = 1;

        wait(bfs_done);
        #10 bfs_start = 0;
                
        #10 x = 1; y = 2; bfs_start = 1;
        wait(bfs_done);

        $display("BFS completed: sink=%b", bfs_sink);
        if (!bfs_sink) $display("BFS sink detection failed - expected sink but got no sink");
        else $display("BFS sink detection PASSED");
        
        $display("BFS verification COMPLETED");
        #40;
        $finish;
    end
endmodule

vcd/tb_bfs.vcd
$date
	Sun Nov  2 18:43:27 2025
$end
$version
	Icarus Verilog
$end
$timescale
	1ps
$end
$scope module tb_bfs $end
$var wire 12 ! row5_mem [11:0] $end
$var wire 12 " row4_mem [11:0] $end
$var wire 12 # row3_mem [11:0] $end
$var wire 12 $ row2_mem [11:0] $end
$var wire 12 % row1_mem [11:0] $end
$var wire 12 & row0_mem [11:0] $end
$var wire 1 ' mem_wr_en $end
$var wire 2 ( mem_wr_data [1:0] $end
$var wire 1 ) mem_in_valid $end
$var wire 72 * mem_flat [71:0] $end
$var wire 3 + mem_addr_y [2:0] $end
$var wire 3 , mem_addr_x [2:0] $end
$var wire 1 - bfs_sink $end
$var wire 1 . bfs_done $end
$var parameter 32 / WIDTH $end
$var reg 1 0 bfs_start $end
$var reg 1 1 clk $end
$var reg 2 2 mem_rd_data [1:0] $end
$var reg 1 3 mem_ready $end
$var reg 1 4 rstn $end
$var reg 3 5 x [2:0] $end
$var reg 3 6 y [2:0] $end
$scope module uut $end
$var wire 1 0 bfs_start $end
$var wire 1 1 clk $end
$var wire 1 7 found $end
$var wire 2 8 mem_rd_data [1:0] $end
$var wire 1 3 mem_ready $end
$var wire 1 4 rstn $end
$var wire 3 9 x [2:0] $end
$var wire 3 : y [2:0] $end
$var wire 3 ; y_upper [2:0] $end
$var wire 3 < y_lower [2:0] $end
$var wire 3 = x_right [2:0] $end
$var wire 3 > x_left [2:0] $end
$var parameter 4 ? BFS_CHECK $end
$var parameter 4 @ BFS_CLEAR $end
$var parameter 4 A BFS_DONE $end
$var parameter 4 B BFS_LOAD $end
$var parameter 3 C CHECK_DELAY $end
$var parameter 3 D CHECK_FOUND $end
$var parameter 3 E CHECK_IDLE $end
$var parameter 4 F DELAY $end
$var parameter 32 G WIDTH $end
$var parameter 3 H X_L $end
$var parameter 3 I X_R $end
$var parameter 3 J Y_D $end
$var parameter 3 K Y_U $end
$var reg 1 . bfs_done $end
$var reg 4 L bfs_next_state [3:0] $end
$var reg 1 - bfs_sink $end
$var reg 4 M bfs_state [3:0] $end
$var reg 64 N bfs_state_name [63:0] $end
$var reg 3 O cell_count [2:0] $end
$var reg 1 P check_done_sig $end
$var reg 3 Q check_next_state [2:0] $end
$var reg 1 R check_start $end
$var reg 3 S check_state [2:0] $end
$var reg 64 T check_state_name [63:0] $end
$var reg 1 U found_gray $end
$var reg 1 V found_white $end
$var reg 3 W gray_x [2:0] $end
$var reg 3 X gray_y [2:0] $end
$var reg 3 Y mem_addr_x [2:0] $end
$var reg 3 Z mem_addr_y [2:0] $end
$var reg 1 ) mem_in_valid $end
$var reg 2 [ mem_wr_data [1:0] $end
$var reg 1 ' mem_wr_en $end
$var reg 3 \ orig_x [2:0] $end
$var reg 3 ] orig_y [2:0] $end
$upscope $end
$scope begin $ivl_for_loop0 $end
$var integer 32 ^ i [31:0] $end
$upscope $end
$upscope $end
$enddefinitions $end
$comment Show the parameter values. $end
$dumpall
b11 K
b100 J
b10 I
b1 H
b110 G
b1111 F
b0 E
b101 D
b110 C
b0 B
b1110 A
b1000 @
b10 ?
b110 /
$end
#0
$dumpvars
b100100 ^
b0 ]
b0 \
b0 [
b0 Z
b0 Y
b0 X
b0 W
0V
0U
b1001001010001000100110001000101 T
b0 S
0R
b0 Q
0P
b0 O
b1001100010011110100000101000100 N
b0 M
b0 L
b0 >
b1 =
b0 <
b1 ;
bx :
bx 9
bx 8
07
bx 6
bx 5
04
03
bx 2
01
00
0.
0-
b0 ,
b0 +
b100000000010100000000000000 *
0)
b0 (
0'
b0 &
b10100 %
b100 $
b0 #
b0 "
b0 !
$end
#5000
11
#10000
01
14
#15000
11
#20000
01
10
b1 6
b1 :
b1 5
b1 9
#25000
b100001101001000010001010100001101001011 N
b10 ;
b10 =
b10 M
b1 ]
b1 \
11
#30000
01
#35000
1R
11
#40000
01
#45000
b1000011010111110100010001000101010011000100000101011001 T
b1 Q
b110 S
1)
b1 +
b1 Z
11
#50000
01
#55000
0)
13
b0 2
b0 8
11
#60000
01
#65000
b10110000101111101001100 T
b1 S
03
11
#70000
01
#75000
b1000011010111110100010001000101010011000100000101011001 T
b10 Q
b110 S
1)
b10 ,
b10 Y
11
#80000
01
#85000
0)
13
b1 2
b1 8
11
#90000
01
#95000
b10110000101111101010010 T
b10 S
03
11
#100000
01
#105000
b1000011010111110100010001000101010011000100000101011001 T
17
b11 Q
b110 S
1)
b10 +
b10 Z
b1 ,
b1 Y
b1 O
1V
11
#110000
01
#115000
0)
13
11
#120000
01
#125000
b10110010101111101010101 T
b11 S
03
11
#130000
01
#135000
b1000011010111110100010001000101010011000100000101011001 T
b100 Q
b110 S
1)
b0 +
b0 Z
b10 O
11
#140000
01
#145000
0)
13
b0 2
b0 8
11
#150000
01
#155000
b10110010101111101000100 T
b100 S
03
11
#160000
01
#165000
b1000011010111110100011001001111010101010100111001000100 T
b101 S
11
#170000
01
#175000
1P
11
#180000
01
#185000
b100010001000101010011000100000101011001 N
b1110 L
b1111 M
1)
b10 (
b10 [
1'
b1 +
b1 Z
0R
11
#190000
01
#195000
b1001001010001000100110001000101 T
0'
0)
0P
b0 S
13
b1 2
b1 8
b100000000011000000000000000 *
b11000 %
11
#200000
01
#205000
b1000100010011110100111001000101 N
b1110 M
03
11
#210000
01
#215000
1.
11
#220000
01
#225000
b1001100010011110100000101000100 N
0.
b0 M
11
00
#230000
01
#235000
b100001101001000010001010100001101001011 N
b11 =
07
b1 >
b0 O
0V
b10 M
b10 \
11
10
b10 5
b10 9
#240000
01
#245000
1R
11
#250000
01
#255000
b1000011010111110100010001000101010011000100000101011001 T
b1 Q
b110 S
1)
11
#260000
01
#265000
0)
13
b10 2
b10 8
11
#270000
01
#275000
b10110000101111101001100 T
b1 S
03
11
#280000
01
#285000
b1000011010111110100010001000101010011000100000101011001 T
17
b10 Q
b110 S
1)
b11 ,
b11 Y
b1 X
b1 W
b1 O
1U
11
#290000
01
#295000
0)
13
b0 2
b0 8
11
#300000
01
#305000
b10110000101111101010010 T
b10 S
03
11
#310000
01
#315000
b1000011010111110100010001000101010011000100000101011001 T
b11 Q
b110 S
1)
b10 +
b10 Z
b10 ,
b10 Y
11
#320000
01
#325000
0)
13
11
#330000
01
#335000
b10110010101111101010101 T
b11 S
03
11
#340000
01
#345000
b1000011010111110100010001000101010011000100000101011001 T
b100 Q
b110 S
1)
b0 +
b0 Z
11
#350000
01
#355000
0)
13
11
#360000
01
#365000
b10110010101111101000100 T
b100 S
03
11
#370000
01
#375000
b1000011010111110100011001001111010101010100111001000100 T
b101 S
11
#380000
01
#385000
1P
11
#390000
01
#395000
b100001101001100010001010100000101010010 N
b1000 M
1)
b0 (
b0 [
1'
b1 +
b1 Z
0R
11
#400000
01
#405000
b1001001010001000100110001000101 T
b100001101001000010001010100001101001011 N
b10 =
07
b0 >
0P
b0 S
b10 M
b0 O
0U
b1 \
13
b1 2
b1 8
b100000000001000000000000000 *
b1000 %
11
#410000
01
#415000
1R
b0 2
b0 8
11
#420000
01
#425000
b1000011010111110100010001000101010011000100000101011001 T
b1 Q
b110 S
0'
b0 ,
b0 Y
11
#430000
01
#435000
b10110000101111101001100 T
b1 S
0)
11
#440000
01
#445000
b1000011010111110100010001000101010011000100000101011001 T
b10 Q
b110 S
1)
b10 ,
b10 Y
03
11
#450000
01
#455000
0)
13
11
#460000
01
#465000
b10110000101111101010010 T
b10 S
03
11
#470000
01
#475000
b1000011010111110100010001000101010011000100000101011001 T
b11 Q
b110 S
1)
b10 +
b10 Z
b1 ,
b1 Y
11
#480000
01
#485000
0)
13
b1 2
b1 8
11
#490000
01
#495000
b10110010101111101010101 T
b11 S
03
11
#500000
01
#505000
b1000011010111110100010001000101010011000100000101011001 T
17
b100 Q
b110 S
1)
b0 +
b0 Z
b1 O
1V
11
#510000
01
#515000
0)
13
b0 2
b0 8
11
#520000
01
#525000
b10110010101111101000100 T
b100 S
03
11
#530000
01
#535000
b1000011010111110100011001001111010101010100111001000100 T
b101 S
11
#540000
01
#545000
1P
11
#550000
01
#555000
b100010001000101010011000100000101011001 N
b1111 M
1)
b10 (
b10 [
1'
b1 +
b1 Z
0R
11
#560000
01
#565000
b1001001010001000100110001000101 T
0P
b0 S
0'
0)
13
b10 2
b10 8
11
#570000
01
#575000
b1000100010011110100111001000101 N
b1110 M
03
11
#580000
01
#585000
1.
11
#590000
01
#595000
b1001100010011110100000101000100 N
0.
b0 M
11
00
#600000
01
#605000
b100001101001000010001010100001101001011 N
b11 ;
07
b1 <
b0 O
0V
b10 M
b10 ]
11
10
b10 6
b10 :
b1 5
b1 9
#610000
01
#615000
1R
11
#620000
01
#625000
b1000011010111110100010001000101010011000100000101011001 T
b1 Q
b110 S
1)
b10 +
b10 Z
b0 ,
b0 Y
11
#630000
01
#635000
0)
13
b0 2
b0 8
11
#640000
01
#645000
b10110000101111101001100 T
b1 S
03
11
#650000
01
#655000
b1000011010111110100010001000101010011000100000101011001 T
b10 Q
b110 S
1)
b10 ,
b10 Y
11
#660000
01
#665000
0)
13
11
#670000
01
#675000
b10110000101111101010010 T
b10 S
03
11
#680000
01
#685000
b1000011010111110100010001000101010011000100000101011001 T
b11 Q
b110 S
1)
b11 +
b11 Z
b1 ,
b1 Y
11
#690000
01
#695000
0)
13
11
#700000
01
#705000
b10110010101111101010101 T
b11 S
03
11
#710000
01
#715000
b1000011010111110100010001000101010011000100000101011001 T
b100 Q
b110 S
1)
b1 +
b1 Z
11
#720000
01
#725000
0)
13
b10 2
b10 8
11
#730000
01
#735000
b10110010101111101000100 T
b100 S
03
11
#740000
01
#745000
b1000011010111110100011001001111010101010100111001000100 T
17
b101 S
b1 O
1U
11
#750000
01
#755000
1P
11
#760000
01
#765000
b100001101001100010001010100000101010010 N
b1000 M
1)
b0 (
b0 [
1'
b10 +
b10 Z
0R
11
#770000
01
#775000
b100001101001000010001010100001101001011 N
b1001001010001000100110001000101 T
b10 ;
07
b0 <
b10 M
b0 O
0U
b1 ]
0P
b0 S
13
b1 2
b1 8
b1000000000000000 *
b0 $
11
#780000
01
#785000
1R
b0 2
b0 8
11
#790000
01
#795000
b1000011010111110100010001000101010011000100000101011001 T
b1 Q
b110 S
0'
b1 +
b1 Z
b0 ,
b0 Y
11
#800000
01
#805000
b10110000101111101001100 T
b1 S
0)
11
#810000
01
#815000
b1000011010111110100010001000101010011000100000101011001 T
b10 Q
b110 S
1)
b10 ,
b10 Y
03
11
#820000
01
#825000
0)
13
11
#830000
01
#835000
b10110000101111101010010 T
b10 S
03
11
#840000
01
#845000
b1000011010111110100010001000101010011000100000101011001 T
b11 Q
b110 S
1)
b10 +
b10 Z
b1 ,
b1 Y
11
#850000
01
#855000
0)
13
11
#860000
01
#865000
b10110010101111101010101 T
b11 S
03
11
#870000
01
#875000
b1000011010111110100010001000101010011000100000101011001 T
b100 Q
b110 S
1)
b0 +
b0 Z
11
#880000
01
#885000
0)
13
11
#890000
01
#895000
b10110010101111101000100 T
b100 S
03
11
#900000
01
#905000
b1000011010111110100011001001111010101010100111001000100 T
b101 S
11
#910000
01
#915000
1P
11
#920000
01
#925000
b100010001000101010011000100000101011001 N
b1111 M
1-
1)
1'
b1 +
b1 Z
0R
11
#930000
01
#935000
b1001001010001000100110001000101 T
0'
0)
0P
b0 S
13
b10 2
b10 8
b0 *
b0 %
11
#940000
01
#945000
b1000100010011110100111001000101 N
b1110 M
03
11
#950000
01
#955000
1.
11
